warn/__init__.py
warn/cache.py
warn/cli.py
warn/runner.py
warn/utils.py
warn/platforms/__init__.py
warn/platforms/job_center/__init__.py
warn/platforms/job_center/cache.py
warn/platforms/job_center/site.py
warn/platforms/job_center/urls.py
warn/platforms/job_center/utils.py
warn/scrapers/__init__.py
warn/scrapers/ak.py
warn/scrapers/al.py
warn/scrapers/az.py
warn/scrapers/ca.py
warn/scrapers/co.py
warn/scrapers/ct.py
warn/scrapers/dc.py
warn/scrapers/de.py
warn/scrapers/fl.py
warn/scrapers/ga.py
warn/scrapers/hi.py
warn/scrapers/ia.py
warn/scrapers/id.py
warn/scrapers/il.py
warn/scrapers/in.py
warn/scrapers/ks.py
warn/scrapers/ky.py
warn/scrapers/la.py
warn/scrapers/md.py
warn/scrapers/me.py
warn/scrapers/mi.py
warn/scrapers/mo.py
warn/scrapers/mt.py
warn/scrapers/ne.py
warn/scrapers/nj.py
warn/scrapers/nm.py
warn/scrapers/ny.py
warn/scrapers/oh.py
warn/scrapers/ok.py
warn/scrapers/or.py
warn/scrapers/pa.py
warn/scrapers/ri.py
warn/scrapers/sc.py
warn/scrapers/sd.py
warn/scrapers/tn.py
warn/scrapers/tx.py
warn/scrapers/ut.py
warn/scrapers/va.py
warn/scrapers/vt.py
warn/scrapers/wa.py
warn/scrapers/wi.py
warn_scraper-1.2.132.dist-info/licenses/LICENSE
warn_scraper-1.2.132.dist-info/METADATA
warn_scraper-1.2.132.dist-info/WHEEL
warn_scraper-1.2.132.dist-info/entry_points.txt
warn_scraper-1.2.132.dist-info/top_level.txt
warn_scraper-1.2.132.dist-info/RECORD
