Metadata-Version: 2.4
Name: warn-scraper
Version: 1.2.132
Summary: Command-line interface for downloading WARN Act notices of qualified plant closings and mass layoffs from state government websites
Author-email: Big Local News <biglocalnews@stanford.edu>
License-Expression: Apache-2.0
Project-URL: Documentation, https://warn-scraper.readthedocs.io
Project-URL: Maintainer, https://github.com/biglocalnews
Project-URL: Source, https://github.com/biglocalnews/warn-scraper
Project-URL: Tracker, https://github.com/biglocalnews/warn-scraper/issues
Keywords: WARN Act,scrapers,WARN Act data,WARN Act scrapers
Classifier: Programming Language :: Python :: 3
License-File: LICENSE
Requires-Dist: click
Requires-Dist: beautifulsoup4
Requires-Dist: html5lib
Requires-Dist: pdfplumber
Requires-Dist: requests
Requires-Dist: openpyxl
Requires-Dist: pyopenssl
Requires-Dist: retry2
Requires-Dist: selenium
Requires-Dist: stealthenium
Requires-Dist: tenacity
Requires-Dist: xlrd
Requires-Dist: xvfbwrapper
Requires-Dist: webdriver-manager
Dynamic: license-file
